[
  {
    "class":"firrtl.EmitCircuitAnnotation",
    "emitter":"firrtl.VerilogEmitter"
  },
  {
    "class":"firrtl.transforms.BlackBoxTargetDirAnno",
    "targetDir":"verilog"
  },
  {
    "class":"firrtl.transforms.CombinationalPath",
    "sink":"~ID|ID>io_wRegDataSrc_ctrl_uMEM_ID",
    "sources":[
      "~ID|ID>io_instr_ID"
    ]
  },
  {
    "class":"firrtl.transforms.CombinationalPath",
    "sink":"~ID|ID>io_weMEM_ctrl_uMEM_ID",
    "sources":[
      "~ID|ID>io_instr_ID"
    ]
  },
  {
    "class":"firrtl.transforms.CombinationalPath",
    "sink":"~ID|ID>io_data2_ID",
    "sources":[
      "~ID|ID>io_wRegData_MEM",
      "~ID|ID>io_aluResult_EXE",
      "~ID|ID>io_wRegAddr_MEM",
      "~ID|ID>io_wRegDataSrc_ctrl_uMEM_EXE",
      "~ID|ID>io_wRegData_WB",
      "~ID|ID>io_instr_ID",
      "~ID|ID>io_wRegAddr_EXE",
      "~ID|ID>io_wRegaddr_WB",
      "~ID|ID>io_wReg_ctrl_uWB_WB"
    ]
  },
  {
    "class":"firrtl.transforms.CombinationalPath",
    "sink":"~ID|ID>io_memReadDataExt_ctrl_uMEM_ID",
    "sources":[
      "~ID|ID>io_instr_ID"
    ]
  },
  {
    "class":"firrtl.transforms.CombinationalPath",
    "sink":"~ID|ID>io_stallReqOfID_ID",
    "sources":[
      "~ID|ID>io_wRegAddr_EXE",
      "~ID|ID>io_wReg_ctrl_uWB_WB",
      "~ID|ID>io_instr_ID"
    ]
  },
  {
    "class":"firrtl.transforms.CombinationalPath",
    "sink":"~ID|ID>io_flushReqOfID_ID",
    "sources":[
      "~ID|ID>io_wRegData_MEM",
      "~ID|ID>io_PC_ID",
      "~ID|ID>io_instr_ID",
      "~ID|ID>io_aluResult_EXE",
      "~ID|ID>io_wRegAddr_MEM",
      "~ID|ID>io_wRegDataSrc_ctrl_uMEM_EXE",
      "~ID|ID>io_wRegData_WB",
      "~ID|ID>io_wRegAddr_EXE",
      "~ID|ID>io_wRegaddr_WB",
      "~ID|ID>io_wReg_ctrl_uWB_WB"
    ]
  },
  {
    "class":"firrtl.transforms.CombinationalPath",
    "sink":"~ID|ID>io_wrMemByteSelScr_ctrl_uMEM_ID",
    "sources":[
      "~ID|ID>io_instr_ID"
    ]
  },
  {
    "class":"firrtl.transforms.CombinationalPath",
    "sink":"~ID|ID>io_aluOP_ctrl_uEXE_ID",
    "sources":[
      "~ID|ID>io_instr_ID"
    ]
  },
  {
    "class":"firrtl.transforms.CombinationalPath",
    "sink":"~ID|ID>io_branchFlag_ID",
    "sources":[
      "~ID|ID>io_wRegData_MEM",
      "~ID|ID>io_PC_ID",
      "~ID|ID>io_instr_ID",
      "~ID|ID>io_aluResult_EXE",
      "~ID|ID>io_wRegAddr_MEM",
      "~ID|ID>io_wRegDataSrc_ctrl_uMEM_EXE",
      "~ID|ID>io_wRegData_WB",
      "~ID|ID>io_wRegAddr_EXE",
      "~ID|ID>io_wRegaddr_WB",
      "~ID|ID>io_wReg_ctrl_uWB_WB"
    ]
  },
  {
    "class":"firrtl.transforms.CombinationalPath",
    "sink":"~ID|ID>io_data1_ID",
    "sources":[
      "~ID|ID>io_wRegData_MEM",
      "~ID|ID>io_PC_ID",
      "~ID|ID>io_aluResult_EXE",
      "~ID|ID>io_wRegAddr_MEM",
      "~ID|ID>io_wRegDataSrc_ctrl_uMEM_EXE",
      "~ID|ID>io_wRegData_WB",
      "~ID|ID>io_instr_ID",
      "~ID|ID>io_wRegAddr_EXE",
      "~ID|ID>io_wRegaddr_WB",
      "~ID|ID>io_wReg_ctrl_uWB_WB"
    ]
  },
  {
    "class":"firrtl.transforms.CombinationalPath",
    "sink":"~ID|ID>io_wMemData_ID",
    "sources":[
      "~ID|ID>io_instr_ID"
    ]
  },
  {
    "class":"firrtl.transforms.CombinationalPath",
    "sink":"~ID|ID>io_branchTarge_ID",
    "sources":[
      "~ID|ID>io_PC_ID",
      "~ID|ID>io_wRegData_MEM",
      "~ID|ID>io_aluResult_EXE",
      "~ID|ID>io_instr_ID",
      "~ID|ID>io_wRegAddr_MEM",
      "~ID|ID>io_wRegDataSrc_ctrl_uMEM_EXE",
      "~ID|ID>io_wRegData_WB",
      "~ID|ID>io_wRegAddr_EXE",
      "~ID|ID>io_wRegaddr_WB",
      "~ID|ID>io_wReg_ctrl_uWB_WB"
    ]
  },
  {
    "class":"firrtl.transforms.CombinationalPath",
    "sink":"~ID|ID>io_weReg_ctrl_uWB_ID",
    "sources":[
      "~ID|ID>io_instr_ID"
    ]
  },
  {
    "class":"firrtl.transforms.CombinationalPath",
    "sink":"~ID|ID>io_wRegAddr_ID",
    "sources":[
      "~ID|ID>io_instr_ID"
    ]
  }
]